text_generation/__init__.py
text_generation/client.py
text_generation/errors.py
text_generation/inference_api.py
text_generation/types.py
text_generation-0.6.0.dist-info/WHEEL
text_generation-0.6.0.dist-info/METADATA
text_generation-0.6.0.dist-info/RECORD
