Metadata-Version: 2.1
Name: text-generation
Version: 0.6.0
Summary: Hugging Face Text Generation Python Client
Home-page: https://github.com/huggingface/text-generation-inference
License: Apache-2.0
Author: Olivier Dehaene
Author-email: olivier@huggingface.co
Maintainer: Olivier Dehaene
Maintainer-email: olivier@huggingface.co
Requires-Python: >=3.7,<4.0
Classifier: License :: OSI Approved :: Apache Software License
Classifier: Programming Language :: Python :: 3
Classifier: Programming Language :: Python :: 3.7
Classifier: Programming Language :: Python :: 3.8
Classifier: Programming Language :: Python :: 3.9
Classifier: Programming Language :: Python :: 3.10
Requires-Dist: aiohttp (>=3.8,<4.0)
Requires-Dist: huggingface-hub (>=0.12,<1.0)
Requires-Dist: pydantic (>=1.10,<2.0)
Project-URL: Repository, https://github.com/huggingface/text-generation-inference
